dearaj/__init__.py
dearaj/ajcore.py
dearaj/data/10_conferences_2022-07-18-18-54-25.csv
dearaj/data/11_conferences_2022-07-18-18-54-04.csv
dearaj/data/12_conferences_2022-07-18-18-53-45.csv
dearaj/data/13_conferences_2022-07-18-18-53-17.csv
dearaj/data/14_conferences_2022-07-18-18-52-54.csv
dearaj/data/15_conferences_2022-07-18-18-52-14.csv
dearaj/data/16_conferences_2022-07-18-18-51-30.csv
dearaj/data/17_conferences_2022-07-18-09-13-27.csv
dearaj/data/18_conferences_2022-07-18-06-21-45.csv
dearaj/data/19_conferences_2022-07-18-06-31-21.csv
dearaj/data/20_conferences_2022-07-18-08-25-42.csv
dearaj/data/6_conferences_2022-07-18-19-14-44.csv
dearaj/data/7_conferences_2022-07-18-19-14-39.csv
dearaj/data/8_conferences_2022-07-18-19-14-30.csv
dearaj/data/9_conferences_2022-07-18-19-09-48.csv
dearaj/data/congressman_list/10_congressman_list.csv
dearaj/data/congressman_list/11_congressman_list.csv
dearaj/data/congressman_list/12_congressman_list.csv
dearaj/data/congressman_list/13_congressman_list.csv
dearaj/data/congressman_list/14_congressman_list.csv
dearaj/data/congressman_list/15_congressman_list.csv
dearaj/data/congressman_list/16_congressman_list.csv
dearaj/data/congressman_list/17_congressman_list.csv
dearaj/data/congressman_list/18_congressman_list.csv
dearaj/data/congressman_list/19_congressman_list.csv
dearaj/data/congressman_list/20_congressman_list.csv
dearaj/data/congressman_list/21_congressman_list.csv
dearaj/data/congressman_list/6_congressman_list.csv
dearaj/data/congressman_list/7_congressman_list.csv
dearaj/data/congressman_list/8_congressman_list.csv
dearaj/data/congressman_list/9_congressman_list.csv
dearaj-0.0.3.dist-info/LICENSE
dearaj-0.0.3.dist-info/METADATA
dearaj-0.0.3.dist-info/WHEEL
dearaj-0.0.3.dist-info/top_level.txt
dearaj-0.0.3.dist-info/RECORD
