Metadata-Version: 2.1
Name: dearaj
Version: 0.0.3
Summary: Data analysis tool for Korean National Assembly
Home-page: https://github.com/anzhi0708/dearAJ
Author: Anji Wong
Author-email: anzhi0708@gmail.com
Classifier: Development Status :: 4 - Beta
Classifier: Programming Language :: Python :: 3.6
Classifier: Programming Language :: Python :: 3.7
Classifier: Programming Language :: Python :: 3.8
Classifier: Programming Language :: Python :: 3.9
Classifier: Programming Language :: Python :: 3.10
Classifier: Intended Audience :: Education
Classifier: Intended Audience :: Science/Research
Classifier: Topic :: Sociology :: History
Classifier: Topic :: Sociology :: Genealogy
Classifier: Topic :: Education :: Testing
Classifier: Topic :: Scientific/Engineering :: Information Analysis
Classifier: License :: OSI Approved :: Apache Software License
Classifier: Operating System :: OS Independent
Classifier: Natural Language :: Korean
Requires-Python: >=3.6
License-File: LICENSE
Requires-Dist: requests
Requires-Dist: faker
